{"frames":{"hoodguy_01":{"frame":{"x":0,"y":128,"w":32,"h":32},"rotated":false,"trimmed":false,"spriteSourceSize":{"x":0,"y":0,"w":32,"h":32},"sourceSize":{"w":32,"h":32}},"hoodguy_02":{"frame":{"x":0,"y":96,"w":32,"h":32},"rotated":false,"trimmed":false,"spriteSourceSize":{"x":0,"y":0,"w":32,"h":32},"sourceSize":{"w":32,"h":32}},"D_idle":{"frame":{"x":96,"y":64,"w":32,"h":32},"rotated":false,"trimmed":false,"spriteSourceSize":{"x":0,"y":0,"w":32,"h":32},"sourceSize":{"w":32,"h":32}},"D_walk_01":{"frame":{"x":192,"y":128,"w":32,"h":32},"rotated":false,"trimmed":false,"spriteSourceSize":{"x":0,"y":0,"w":32,"h":32},"sourceSize":{"w":32,"h":32}},"D_walk_02":{"frame":{"x":0,"y":32,"w":32,"h":32},"rotated":false,"trimmed":false,"spriteSourceSize":{"x":0,"y":0,"w":32,"h":32},"sourceSize":{"w":32,"h":32}},"L_idle":{"frame":{"x":32,"y":64,"w":32,"h":32},"rotated":false,"trimmed":false,"spriteSourceSize":{"x":0,"y":0,"w":32,"h":32},"sourceSize":{"w":32,"h":32}},"L_walk_01":{"frame":{"x":160,"y":160,"w":32,"h":32},"rotated":false,"trimmed":false,"spriteSourceSize":{"x":0,"y":0,"w":32,"h":32},"sourceSize":{"w":32,"h":32}},"L_walk_02":{"frame":{"x":64,"y":96,"w":32,"h":32},"rotated":false,"trimmed":false,"spriteSourceSize":{"x":0,"y":0,"w":32,"h":32},"sourceSize":{"w":32,"h":32}},"R_idle":{"frame":{"x":160,"y":128,"w":32,"h":32},"rotated":false,"trimmed":false,"spriteSourceSize":{"x":0,"y":0,"w":32,"h":32},"sourceSize":{"w":32,"h":32}},"R_walk_01":{"frame":{"x":96,"y":128,"w":32,"h":32},"rotated":false,"trimmed":false,"spriteSourceSize":{"x":0,"y":0,"w":32,"h":32},"sourceSize":{"w":32,"h":32}},"R_walk_02":{"frame":{"x":32,"y":32,"w":32,"h":32},"rotated":false,"trimmed":false,"spriteSourceSize":{"x":0,"y":0,"w":32,"h":32},"sourceSize":{"w":32,"h":32}},"U_idle":{"frame":{"x":128,"y":64,"w":32,"h":32},"rotated":false,"trimmed":false,"spriteSourceSize":{"x":0,"y":0,"w":32,"h":32},"sourceSize":{"w":32,"h":32}},"U_walk_01":{"frame":{"x":120,"y":160,"w":32,"h":32},"rotated":false,"trimmed":false,"spriteSourceSize":{"x":0,"y":0,"w":32,"h":32},"sourceSize":{"w":32,"h":32}},"U_walk_02":{"frame":{"x":192,"y":64,"w":32,"h":32},"rotated":false,"trimmed":false,"spriteSourceSize":{"x":0,"y":0,"w":32,"h":32},"sourceSize":{"w":32,"h":32}},"item_01":{"frame":{"x":152,"y":200,"w":32,"h":32},"rotated":false,"trimmed":false,"spriteSourceSize":{"x":0,"y":0,"w":32,"h":32},"sourceSize":{"w":32,"h":32}},"item_02":{"frame":{"x":128,"y":128,"w":32,"h":32},"rotated":false,"trimmed":false,"spriteSourceSize":{"x":0,"y":0,"w":32,"h":32},"sourceSize":{"w":32,"h":32}},"item_03":{"frame":{"x":32,"y":96,"w":32,"h":32},"rotated":false,"trimmed":false,"spriteSourceSize":{"x":0,"y":0,"w":32,"h":32},"sourceSize":{"w":32,"h":32}},"item_04":{"frame":{"x":128,"y":96,"w":32,"h":32},"rotated":false,"trimmed":false,"spriteSourceSize":{"x":0,"y":0,"w":32,"h":32},"sourceSize":{"w":32,"h":32}},"item_05":{"frame":{"x":32,"y":128,"w":32,"h":32},"rotated":false,"trimmed":false,"spriteSourceSize":{"x":0,"y":0,"w":32,"h":32},"sourceSize":{"w":32,"h":32}},"item_06":{"frame":{"x":0,"y":0,"w":32,"h":32},"rotated":false,"trimmed":false,"spriteSourceSize":{"x":0,"y":0,"w":32,"h":32},"sourceSize":{"w":32,"h":32}},"item_08":{"frame":{"x":64,"y":64,"w":32,"h":32},"rotated":false,"trimmed":false,"spriteSourceSize":{"x":0,"y":0,"w":32,"h":32},"sourceSize":{"w":32,"h":32}},"item_09":{"frame":{"x":160,"y":64,"w":32,"h":32},"rotated":false,"trimmed":false,"spriteSourceSize":{"x":0,"y":0,"w":32,"h":32},"sourceSize":{"w":32,"h":32}},"item_07":{"frame":{"x":0,"y":64,"w":32,"h":32},"rotated":false,"trimmed":false,"spriteSourceSize":{"x":0,"y":0,"w":32,"h":32},"sourceSize":{"w":32,"h":32}},"credits_00":{"frame":{"x":0,"y":280,"w":190,"h":40},"rotated":false,"trimmed":false,"spriteSourceSize":{"x":0,"y":0,"w":190,"h":40},"sourceSize":{"w":190,"h":40}},"credits_01":{"frame":{"x":0,"y":240,"w":190,"h":40},"rotated":false,"trimmed":false,"spriteSourceSize":{"x":0,"y":0,"w":190,"h":40},"sourceSize":{"w":190,"h":40}},"play_00":{"frame":{"x":0,"y":200,"w":120,"h":40},"rotated":false,"trimmed":false,"spriteSourceSize":{"x":0,"y":0,"w":120,"h":40},"sourceSize":{"w":120,"h":40}},"play_01":{"frame":{"x":0,"y":160,"w":120,"h":40},"rotated":false,"trimmed":false,"spriteSourceSize":{"x":0,"y":0,"w":120,"h":40},"sourceSize":{"w":120,"h":40}},"firefly_01":{"frame":{"x":32,"y":0,"w":32,"h":32},"rotated":false,"trimmed":false,"spriteSourceSize":{"x":0,"y":0,"w":32,"h":32},"sourceSize":{"w":32,"h":32}},"firefly_02":{"frame":{"x":160,"y":96,"w":32,"h":32},"rotated":false,"trimmed":false,"spriteSourceSize":{"x":0,"y":0,"w":32,"h":32},"sourceSize":{"w":32,"h":32}},"firefly_03":{"frame":{"x":96,"y":96,"w":32,"h":32},"rotated":false,"trimmed":false,"spriteSourceSize":{"x":0,"y":0,"w":32,"h":32},"sourceSize":{"w":32,"h":32}},"firefly_04":{"frame":{"x":190,"y":280,"w":32,"h":32},"rotated":false,"trimmed":false,"spriteSourceSize":{"x":0,"y":0,"w":32,"h":32},"sourceSize":{"w":32,"h":32}},"firefly_05":{"frame":{"x":64,"y":128,"w":32,"h":32},"rotated":false,"trimmed":false,"spriteSourceSize":{"x":0,"y":0,"w":32,"h":32},"sourceSize":{"w":32,"h":32}},"firefly_06":{"frame":{"x":120,"y":200,"w":32,"h":32},"rotated":false,"trimmed":false,"spriteSourceSize":{"x":0,"y":0,"w":32,"h":32},"sourceSize":{"w":32,"h":32}},"firefly_07":{"frame":{"x":192,"y":96,"w":32,"h":32},"rotated":false,"trimmed":false,"spriteSourceSize":{"x":0,"y":0,"w":32,"h":32},"sourceSize":{"w":32,"h":32}},"smoke_01":{"frame":{"x":96,"y":0,"w":32,"h":64},"rotated":false,"trimmed":false,"spriteSourceSize":{"x":0,"y":0,"w":32,"h":64},"sourceSize":{"w":32,"h":64}},"smoke_02":{"frame":{"x":160,"y":0,"w":32,"h":64},"rotated":false,"trimmed":false,"spriteSourceSize":{"x":0,"y":0,"w":32,"h":64},"sourceSize":{"w":32,"h":64}},"smoke_03":{"frame":{"x":64,"y":0,"w":32,"h":64},"rotated":false,"trimmed":false,"spriteSourceSize":{"x":0,"y":0,"w":32,"h":64},"sourceSize":{"w":32,"h":64}},"smoke_04":{"frame":{"x":192,"y":160,"w":32,"h":64},"rotated":false,"trimmed":false,"spriteSourceSize":{"x":0,"y":0,"w":32,"h":64},"sourceSize":{"w":32,"h":64}},"smoke_05":{"frame":{"x":192,"y":0,"w":32,"h":64},"rotated":false,"trimmed":false,"spriteSourceSize":{"x":0,"y":0,"w":32,"h":64},"sourceSize":{"w":32,"h":64}},"smoke_06":{"frame":{"x":128,"y":0,"w":32,"h":64},"rotated":false,"trimmed":false,"spriteSourceSize":{"x":0,"y":0,"w":32,"h":64},"sourceSize":{"w":32,"h":64}}},"meta":{"app":"https://www.leshylabs.com/apps/sstool/","version":"Leshy SpriteSheet Tool v0.8.4","image":"sprite_atlas.png","size":{"w":224,"h":320},"scale":1}}